.commit_date
LICENSE
MANIFEST.in
README.md
requirements.txt
setup.cfg
setup.py
nhentai_data/__init__.py
nhentai_downloader/__init__.py
nhentai_downloader/auth.py
nhentai_downloader/cli.py
nhentai_downloader/constant.py
nhentai_downloader/doujinshi.py
nhentai_downloader/download.py
nhentai_downloader/fetcher.py
nhentai_downloader/io_utils.py
nhentai_downloader/logger.py
nhentai_downloader/nhentai.py
nhentai_downloader.egg-info/PKG-INFO
nhentai_downloader.egg-info/SOURCES.txt
nhentai_downloader.egg-info/dependency_links.txt
nhentai_downloader.egg-info/entry_points.txt
nhentai_downloader.egg-info/not-zip-safe
nhentai_downloader.egg-info/requires.txt
nhentai_downloader.egg-info/top_level.txt