Metadata-Version: 2.1
Name: nhentai-downloader
Version: 0.5.5.2
Summary: Nhentai doujinshi fetcher and downloader
Home-page: https://gitlab.com/DukeValentine/nhentai-downloader
Author: DukeValentine
Author-email: humanix@posteo.de
License: Apache
Download-URL: https://gitlab.com/DukeValentine/nhentai-downloader/-/archive/master/nhentai-downloader-master.tar.gz
Keywords: nhentai,doujinshi
Platform: UNKNOWN
Classifier: Development Status :: 4 - Beta
Classifier: License :: OSI Approved :: Apache Software License
Classifier: Programming Language :: Python :: 3.7
Classifier: Operating System :: OS Independent
Classifier: Topic :: Internet :: WWW/HTTP :: Indexing/Search
